martian_api/__init__.py
martian_api/martian_api.py
martian_api-1.0.4.dist-info/LICENSE
martian_api-1.0.4.dist-info/METADATA
martian_api-1.0.4.dist-info/WHEEL
martian_api-1.0.4.dist-info/top_level.txt
martian_api-1.0.4.dist-info/RECORD
