Metadata-Version: 2.1
Name: martian-api
Version: 1.0.4
Summary: The martian python library allows developers to easily access the martian api.
Author-email: Shriyash Upadhyay <yash@withmartian.com>, Etan Ginsberg <etan@withmartian.com>
Project-URL: Homepage, https://github.com/withmartian/api
Classifier: Programming Language :: Python :: 3
Classifier: Operating System :: OS Independent
Requires-Python: >=3.0
License-File: LICENSE
Requires-Dist: requests (==2.28.1)
